pythainlp/__init__.py
pythainlp/__main__.py
pythainlp/ancient/__init__.py
pythainlp/ancient/aksonhan.py
pythainlp/augment/__init__.py
pythainlp/augment/wordnet.py
pythainlp/augment/lm/__init__.py
pythainlp/augment/lm/fasttext.py
pythainlp/augment/lm/phayathaibert.py
pythainlp/augment/lm/wangchanberta.py
pythainlp/augment/word2vec/__init__.py
pythainlp/augment/word2vec/bpemb_wv.py
pythainlp/augment/word2vec/core.py
pythainlp/augment/word2vec/ltw2v.py
pythainlp/augment/word2vec/thai2fit.py
pythainlp/benchmarks/__init__.py
pythainlp/benchmarks/word_tokenization.py
pythainlp/chat/__init__.py
pythainlp/chat/core.py
pythainlp/classify/__init__.py
pythainlp/classify/param_free.py
pythainlp/cli/__init__.py
pythainlp/cli/benchmark.py
pythainlp/cli/data.py
pythainlp/cli/soundex.py
pythainlp/cli/tag.py
pythainlp/cli/tokenize.py
pythainlp/cls/__init__.py
pythainlp/coref/__init__.py
pythainlp/coref/_fastcoref.py
pythainlp/coref/core.py
pythainlp/coref/han_coref.py
pythainlp/corpus/__init__.py
pythainlp/corpus/blackboard-cls_v1.0.crfsuite
pythainlp/corpus/common.py
pythainlp/corpus/conceptnet.py
pythainlp/corpus/core.py
pythainlp/corpus/corpus_license.md
pythainlp/corpus/countries_th.txt
pythainlp/corpus/crfchunk_orchidpp.model
pythainlp/corpus/default_db.json
pythainlp/corpus/etcc.txt
pythainlp/corpus/family_names_th.txt
pythainlp/corpus/han_solo.crfsuite
pythainlp/corpus/icu.py
pythainlp/corpus/icubrk_th.txt
pythainlp/corpus/negations_th.txt
pythainlp/corpus/orst_words_th.txt
pythainlp/corpus/oscar.py
pythainlp/corpus/person_names_female_th.txt
pythainlp/corpus/person_names_male_th.txt
pythainlp/corpus/pos_orchid_perceptron.json
pythainlp/corpus/pos_orchid_unigram.json
pythainlp/corpus/pos_ud_perceptron-v0.2.json
pythainlp/corpus/pos_ud_unigram-v0.2.json
pythainlp/corpus/sentenceseg_crfcut.model
pythainlp/corpus/stopwords_th.txt
pythainlp/corpus/syllables_th.txt
pythainlp/corpus/th_en_translit.py
pythainlp/corpus/th_en_transliteration_v1.4.tsv
pythainlp-5.0.5.dist-info/LICENSE
pythainlp-5.0.5.dist-info/METADATA
pythainlp-5.0.5.dist-info/WHEEL
pythainlp-5.0.5.dist-info/entry_points.txt
pythainlp-5.0.5.dist-info/top_level.txt
pythainlp-5.0.5.dist-info/RECORD
