Metadata-Version: 2.1
Name: pythainlp
Version: 5.0.5
Summary: Thai Natural Language Processing library
Home-page: https://github.com/PyThaiNLP/pythainlp
Author: PyThaiNLP
Author-email: email@wannaphong.com
License: Apache Software License 2.0
Project-URL: Documentation, https://pythainlp.github.io/docs/5.0/
Project-URL: Tutorials, https://pythainlp.github.io/tutorials/
Project-URL: Source Code, https://github.com/PyThaiNLP/pythainlp
Project-URL: Bug Tracker, https://github.com/PyThaiNLP/pythainlp/issues
Keywords: pythainlp,NLP,natural language processing,text analytics,text processing,localization,computational linguistics,ThaiNLP,Thai NLP,Thai language
Platform: UNKNOWN
Classifier: Development Status :: 5 - Production/Stable
Classifier: Programming Language :: Python :: 3
Classifier: Intended Audience :: Developers
Classifier: License :: OSI Approved :: Apache Software License
Classifier: Natural Language :: Thai
Classifier: Topic :: Scientific/Engineering :: Artificial Intelligence
Classifier: Topic :: Text Processing
Classifier: Topic :: Text Processing :: General
Classifier: Topic :: Text Processing :: Linguistic
Requires-Python: >=3.7
Provides-Extra: attacut
Provides-Extra: benchmarks
Provides-Extra: icu
Provides-Extra: ipa
Provides-Extra: ml
Provides-Extra: ssg
Provides-Extra: thai2fit
Provides-Extra: thai2rom
Provides-Extra: translate
Provides-Extra: wunsen
Provides-Extra: textaugment
Provides-Extra: wangchanberta
Provides-Extra: mt5
Provides-Extra: wtp
Provides-Extra: wordnet
Provides-Extra: generate
Provides-Extra: sefr_cut
Provides-Extra: spell
Provides-Extra: oskut
Provides-Extra: nlpo3
Provides-Extra: onnx
Provides-Extra: thai_nner
Provides-Extra: esupar
Provides-Extra: spacy_thai
Provides-Extra: transformers_ud
Provides-Extra: dependency_parsing
Provides-Extra: coreference_resolution
Provides-Extra: word_approximation
Provides-Extra: wangchanglm
Provides-Extra: wsd
Provides-Extra: el
Provides-Extra: abbreviation
Provides-Extra: full
